kubetail/__init__.py
kubetail-0.0.1.dist-info/licenses/LICENSE
kubetail-0.0.1.dist-info/METADATA
kubetail-0.0.1.dist-info/WHEEL
kubetail-0.0.1.dist-info/top_level.txt
kubetail-0.0.1.dist-info/RECORD
