Metadata-Version: 2.4
Name: kubetail
Version: 0.0.1
Summary: Python SDK for Kubetail - Coming Soon
Author-email: Kubetail <hello@kubetail.com>
License: MIT
Project-URL: Homepage, https://github.com/kubetail-com/kubetail
Project-URL: Repository, https://github.com/kubetail-com/kubetail
Keywords: kubetail,kubernetes,logging
Classifier: Development Status :: 1 - Planning
Classifier: Intended Audience :: Developers
Classifier: License :: OSI Approved :: MIT License
Classifier: Programming Language :: Python :: 3
Classifier: Programming Language :: Python :: 3.7
Classifier: Programming Language :: Python :: 3.8
Classifier: Programming Language :: Python :: 3.9
Classifier: Programming Language :: Python :: 3.10
Classifier: Programming Language :: Python :: 3.11
Classifier: Programming Language :: Python :: 3.12
Requires-Python: >=3.7
License-File: LICENSE
Dynamic: license-file
